MANIFEST.in
README.rst
setup.cfg
setup.py
collective/__init__.py
collective.flowplayerclipviews.egg-info/PKG-INFO
collective.flowplayerclipviews.egg-info/SOURCES.txt
collective.flowplayerclipviews.egg-info/dependency_links.txt
collective.flowplayerclipviews.egg-info/entry_points.txt
collective.flowplayerclipviews.egg-info/namespace_packages.txt
collective.flowplayerclipviews.egg-info/not-zip-safe
collective.flowplayerclipviews.egg-info/requires.txt
collective.flowplayerclipviews.egg-info/top_level.txt
collective/flowplayerclipviews/__init__.py
collective/flowplayerclipviews/configure.zcml
collective/flowplayerclipviews/interfaces.py
collective/flowplayerclipviews/view_stats.py
collective/flowplayerclipviews/Extensions/install.py
collective/flowplayerclipviews/browser/__init__.py
collective/flowplayerclipviews/browser/clip_views.pt
collective/flowplayerclipviews/browser/clip_views.py
collective/flowplayerclipviews/browser/configure.zcml
collective/flowplayerclipviews/browser/view.py
collective/flowplayerclipviews/browser/collective.flowplayerclipviews/clip-views.css
collective/flowplayerclipviews/browser/collective.flowplayerclipviews/flowplayerclipviews.js
collective/flowplayerclipviews/locales/collective.flowplayerclipviews.pot
collective/flowplayerclipviews/locales/rebuild.sh
collective/flowplayerclipviews/locales/it/LC_MESSAGES/collective.flowplayerclipviews.mo
collective/flowplayerclipviews/locales/it/LC_MESSAGES/collective.flowplayerclipviews.po
collective/flowplayerclipviews/profiles/default/cssregistry.xml
collective/flowplayerclipviews/profiles/default/jsregistry.xml
collective/flowplayerclipviews/profiles/default/metadata.xml
collective/flowplayerclipviews/profiles/uninstall/cssregistry.xml
collective/flowplayerclipviews/profiles/uninstall/jsregistry.xml
docs/HISTORY.txt
docs/INSTALL.txt
docs/LICENSE.GPL
docs/LICENSE.txt