Metadata-Version: 1.0
Name: collective.flowplayerclipviews
Version: 0.1.0a
Summary: Plugin for Plone and collective.flowplayer. Get statistics on how many times the video has been seen
Home-page: http://github.com/keul/collective.flowplayerclipviews
Author: keul
Author-email: luca@keul.it
License: GPL
Keywords: flowplayer video views statistic clip
Platform: UNKNOWN
Classifier: Development Status :: 3 - Alpha
Classifier: Framework :: Plone
Classifier: Framework :: Plone :: 4.1
Classifier: Topic :: Multimedia :: Video
Classifier: Programming Language :: Python
Classifier: Programming Language :: JavaScript
